autodebater/__init__.py
autodebater/debate.py
autodebater/debate_runners.py
autodebater/defaults.py
autodebater/defaults.yaml
autodebater/dialogue.py
autodebater/errors.py
autodebater/llm.py
autodebater/participants.py
autodebater/run_debates.py
autodebater/scoring.py
autodebater-0.1.14.dist-info/LICENSE
autodebater-0.1.14.dist-info/METADATA
autodebater-0.1.14.dist-info/WHEEL
autodebater-0.1.14.dist-info/entry_points.txt
autodebater-0.1.14.dist-info/RECORD
