Metadata-Version: 2.1
Name: autodebater
Version: 0.1.14
Summary: Library and CLI for debating LLMs
License: MIT
Author: Neal Lewis
Author-email: imneal@gmail.com
Requires-Python: >=3.10,<3.13
Classifier: License :: OSI Approved :: MIT License
Classifier: Programming Language :: Python :: 3
Classifier: Programming Language :: Python :: 3.10
Classifier: Programming Language :: Python :: 3.11
Classifier: Programming Language :: Python :: 3.12
Requires-Dist: langchain-openai (>=0.1.8,<0.2.0)
Requires-Dist: pyyaml (>=6.0.1,<7.0.0)
Requires-Dist: typer (>=0.12.3,<0.13.0)
